CHANGELOG.txt
LICENSE.txt
MANIFEST.in
README.md
setup.py
chadclock/__init__.py
chadclock.egg-info/PKG-INFO
chadclock.egg-info/SOURCES.txt
chadclock.egg-info/dependency_links.txt
chadclock.egg-info/requires.txt
chadclock.egg-info/top_level.txt