Metadata-Version: 1.1
Name: chadclock
Version: 0.0.3
Summary: chad clock
Home-page: UNKNOWN
Author: Andrew
Author-email: achen08@email.wm.edu
License: MIT
Keywords: chad
Platform: UNKNOWN
Classifier: Development Status :: 5 - Production/Stable
Classifier: Intended Audience :: Education
Classifier: Operating System :: Microsoft :: Windows :: Windows 10
Classifier: License :: OSI Approved :: MIT License
Classifier: Programming Language :: Python :: 3
